yapper/__init__.py
yapper/cli.py
yapper/handler.py
yapper/parser.py
yapper/py.typed
yapper/stubs/.gitkeep
yapper-0.5.0.dist-info/LICENSE.txt
yapper-0.5.0.dist-info/METADATA
yapper-0.5.0.dist-info/WHEEL
yapper-0.5.0.dist-info/entry_points.txt
yapper-0.5.0.dist-info/top_level.txt
yapper-0.5.0.dist-info/RECORD
