Metadata-Version: 2.1
Name: yapper
Version: 0.5.0
Summary: Parser for converting python docstrings to .astro files for the Astro static site generator.
Author-email: Gareth Simons <info@benchmarkurbanism.com>
Maintainer-email: Gareth Simons <info@benchmarkurbanism.com>
License: MIT
Project-URL: homepage, https://github.com/benchmark-urbanism/yapper
Project-URL: documentation, https://github.com/benchmark-urbanism/yapper
Project-URL: repository, https://github.com/benchmark-urbanism/yapper
Keywords: python,static-site-generator,astro,parser,documentation,docstrings
Classifier: Programming Language :: Python
Requires-Python: <4.0,>=3.8
License-File: LICENSE.txt
Requires-Dist: dominate (<3.0.0,>=2.6.0)
Requires-Dist: python-slugify (<7.0.0,>=6.1.1)
Requires-Dist: Markdown (<4.0.0,>=3.3.6)
Requires-Dist: toml (>=0.10.2)
Requires-Dist: griffe (>=0.25.2)
